Metadata-Version: 2.1
Name: music-uri-alarm-clock
Version: 0.1.2
Summary: A beautiful Spotify alarm clock for macOS
Home-page: https://github.com/Md-Arman-Hossain-007/music-alarm-clock.git
Author: Md. Arman Hossain
Author-email: armanhossain.tech@gmail.com
Classifier: Programming Language :: Python :: 3
Classifier: License :: OSI Approved :: MIT License
Classifier: Operating System :: MacOS
Requires-Python: >=3.6
License-File: LICENSE
